IntrinsicDimEstimator/__init__.py
IntrinsicDimEstimator/intrinsic_dimention.py
IntrinsicDimEstimator/test.py
IntrinsicDimEstimator-0.3.2.dist-info/LICENSE.txt
IntrinsicDimEstimator-0.3.2.dist-info/METADATA
IntrinsicDimEstimator-0.3.2.dist-info/WHEEL
IntrinsicDimEstimator-0.3.2.dist-info/top_level.txt
IntrinsicDimEstimator-0.3.2.dist-info/RECORD
