Metadata-Version: 2.1
Name: IntrinsicDimEstimator
Version: 0.3.2
Summary: Intrinsic Dimensionality Estimation with idPettis Method
Author: Eng. Alberto Biscalchin
Author-email: <biscalchin.mau.se@gmail.com>
Keywords: intrinsic dimensionality,dimensionality estimation,data analysis,machine learning
Classifier: Development Status :: 4 - Beta
Classifier: Intended Audience :: Science/Research
Classifier: Programming Language :: Python :: 3
Classifier: Operating System :: OS Independent
License-File: LICENSE.txt
Requires-Dist: numpy
Requires-Dist: scikit-learn
Requires-Dist: scipy
Requires-Dist: matplotlib
